AndorSifReader/_AndorSifReader.py
AndorSifReader/__init__.py
AndorSifReader-1.0.1.dist-info/DESCRIPTION.rst
AndorSifReader-1.0.1.dist-info/METADATA
AndorSifReader-1.0.1.dist-info/RECORD
AndorSifReader-1.0.1.dist-info/WHEEL
AndorSifReader-1.0.1.dist-info/metadata.json
AndorSifReader-1.0.1.dist-info/top_level.txt
